ViviHttpKits/HttpServer.exe
ViviHttpKits/HttpServer.exe.config
ViviHttpKits/HttpServer.pdb
ViviHttpKits/HttpServerLib.dll
ViviHttpKits/HttpServerLib.pdb
ViviHttpKits/Microsoft.Web.WebView2.Core.dll
ViviHttpKits/Microsoft.Web.WebView2.WinForms.dll
ViviHttpKits/Microsoft.Web.WebView2.Wpf.dll
ViviHttpKits/TaskBar.deps.json
ViviHttpKits/TaskBar.dll
ViviHttpKits/TaskBar.exe
ViviHttpKits/TaskBar.pdb
ViviHttpKits/TaskBar.runtimeconfig.json
ViviHttpKits/__init__.py
vivi_http_kits-1.1.1.dist-info/LICENSE
vivi_http_kits-1.1.1.dist-info/METADATA
vivi_http_kits-1.1.1.dist-info/WHEEL
vivi_http_kits-1.1.1.dist-info/dependency_links.txt
vivi_http_kits-1.1.1.dist-info/entry_points.txt
vivi_http_kits-1.1.1.dist-info/namespace_packages.txt
vivi_http_kits-1.1.1.dist-info/top_level.txt
vivi_http_kits-1.1.1.dist-info/RECORD
